{"versionInfo": {"hasModuleVersionChanged": false, "hasApiVersionChanged": false}, "data": {"ProductOut": {"Overview": {"Name": "Elinas Griekse stijl yoghurt aardbei 4-pack", "Subtitle": "Per Set 600 g  (per kilo \u20ac3.82)", "Brand": "Elinas", "Slug": "elinas-griekse-stijl-yoghurt-aardbei-4-pack-set-600-g-322966", "Image": {"Label": "Elinas Griekse stijl yoghurt aardbei 4-pack 600 Gram", "URL": "https://images.ctfassets.net/s0lodsnpsezb/322966_M/e7efc4b21a5d90b5134f5197d52ad35a/322966.png"}, "Meta": {"Description": "Bestel Elinas Griekse stijl yoghurt aardbei 4-pack 600 Gram online op plus.nl. Laat je boodschappen makkelijk en snel thuis bezorgen of haal het op bij jouw PLUS.", "Title": "Elinas Griekse stijl yoghurt aardbei 4-pack 600 Gram - PLUS"}, "IsNIX18": false, "Price": "2.29", "BaseUnitPrice": "3.82", "LineItem": {"Id": "0", "Quantity": 0}, "IsOfflineSaleOnly": false, "IsServiceItem": false, "IsAvailableInStore": true, "MaxOrderLimit": 199, "IsNoIndex": false, "IsLocalItem": false}, "ProductClassificationId": "Standaard", "Categories": {"List": [{"Name": "Zuivel, eieren, boter"}, {"Name": "Verse zuivel"}, {"Name": "Yoghurt"}]}, "Logos": {"PDPInUpperLeft": {"List": [], "EmptyListItem": {"Name": "", "LongDescription": "", "URL": "", "Order": 0}}, "PDPInProductInformation": {"List": [], "EmptyListItem": {"Name": "", "LongDescription": "", "URL": "", "Order": 0}}, "PDPBehindSizeUnit": {"List": [], "EmptyListItem": {"Name": "", "LongDescription": "", "URL": "", "Order": 0}}, "PDPBelowAddToCart": {"List": [], "EmptyListItem": {"Name": "", "LongDescription": "", "URL": "", "Order": 0}}, "PDPAboveTitle": {"List": [], "EmptyListItem": {"Name": "", "LongDescription": "", "URL": "", "Order": 0}}, "PDPInRemarks": {"List": [], "EmptyListItem": {"Name": "", "LongDescription": "", "URL": "", "Order": 0}}}, "Legal": {"RegulatedName": "Yoghurtproduct op Griekse wijze met 9% aardbeien, 9,4% vet in het melkaandeel.", "HealthClaim": "", "DrainWeight": {"UoM": "", "Value": 0}, "RequiredNotificationByLaw": "", "AppointedAuthority": "", "AdittionalClassification": {"System": "", "Trades": ""}}, "UsageDuring": {"BreastFeeding": "", "Pregnancy": "", "SafePeriodAfterOpening": 0}, "Marketing": {"Description": "", "UniqueSellingPoint": "", "Message": "600g (4x150g) \u212e"}, "SupplierContact": {"LegalContact": {"Address": "D-54424 Thalfang", "Name": "Hochwald Foods GmbH"}, "LegalSupplier": {"Address": "", "Name": ""}, "PDP_ProductMeans": {"Email_List": {"List": [], "EmptyListItem": ""}, "SocialMedia_List": {"List": [], "EmptyListItem": ""}, "Contact_List": {"List": [], "EmptyListItem": ""}, "WebSites_List": {"List": [], "EmptyListItem": ""}}}, "Composition": "", "Ingredients": "Ingredi\u00ebnten: YOGHURT, vruchtenbereiding (aardbeien, suiker, kleurend concentraat van vruchten en groenten (zwarte bes, wortel), gemodificeerd zetmeel, verdikkingsmiddelen (E440, E410), zuurteregelaar (E330), aroma), suiker\nKan sporen van SCHAALVRUCHTEN bevatten.", "Nutrient": {"Base": {"UoM": "gram", "Value": 100}, "Additional": {"NutricionalClaim": "", "PreparedDeviation": "Deze waarden gelden voor het niet bereide product", "ReferenceIntake": "(% van de voedingsreferentiewaarde)"}, "Nutrients": {"List": [{"TypeCode": "", "UnitCode": "", "Description": "Energie KJ", "ParentCode": "", "DailyValueIntakePercent": "", "QuantityContained": {"Value": "561.0", "UoM": "kilojoule"}, "SortOrder": 0}, {"TypeCode": "", "UnitCode": "", "Description": "Energie KC", "ParentCode": "", "DailyValueIntakePercent": "", "QuantityContained": {"Value": "134.0", "UoM": "KC"}, "SortOrder": 0}, {"TypeCode": "", "UnitCode": "", "Description": "Vet", "ParentCode": "", "DailyValueIntakePercent": "", "QuantityContained": {"Value": "7.4", "UoM": "gram"}, "SortOrder": 0}, {"TypeCode": "", "UnitCode": "", "Description": "Waarvan verzadigd vet", "ParentCode": "FAT", "DailyValueIntakePercent": "", "QuantityContained": {"Value": "4.9", "UoM": "gram"}, "SortOrder": 0}, {"TypeCode": "", "UnitCode": "", "Description": "Koolhydraten", "ParentCode": "", "DailyValueIntakePercent": "", "QuantityContained": {"Value": "13.7", "UoM": "gram"}, "SortOrder": 0}, {"TypeCode": "", "UnitCode": "", "Description": "Waarvan suikers", "ParentCode": "CHOAVL", "DailyValueIntakePercent": "", "QuantityContained": {"Value": "13.2", "UoM": "gram"}, "SortOrder": 0}, {"TypeCode": "", "UnitCode": "", "Description": "Eiwitten", "ParentCode": "", "DailyValueIntakePercent": "", "QuantityContained": {"Value": "2.7", "UoM": "gram"}, "SortOrder": 0}, {"TypeCode": "", "UnitCode": "", "Description": "Zout", "ParentCode": "", "DailyValueIntakePercent": "", "QuantityContained": {"Value": "0.1", "UoM": "gram"}, "SortOrder": 0}, {"TypeCode": "", "UnitCode": "", "Description": "Calcium", "ParentCode": "", "DailyValueIntakePercent": "13.0", "QuantityContained": {"Value": "100.0", "UoM": "milligram"}, "SortOrder": 0}]}}, "Allergen": {"Warning": "", "Description_Contains": "Melk", "Description_MayContain": "Noten"}, "InstructionsAndSuggestions": {"Instructions": {"Preparation": "", "Storage": "Ongeopend ten minste houdbaar tot: zie bovenkant. Gekoeld bewaren, max 7 \u00b0C.", "Usage": ""}, "Suggestions": {"Serving": ""}}, "PercentageOfAlcohol": "", "Beer": {"Kind": "", "Taste": "", "FoodAdvice": "", "Description": {"Long": "", "Short": ""}}, "Wine": {"Type": "", "Quote": "", "LongDescription": "", "Flavour": "", "GrapeVariety": "", "Country": "", "Region": "", "WineTastingNote": {"FoodAdvice": "", "SmellAndTaste": "", "FoodAdvices": {"List": [], "EmptyListItem": ""}}, "Awards": {"List": [], "EmptyListItem": ""}}, "SeaFood": {"Production": {"Method": ""}, "Catch": {"Areas": "", "Methods": ""}}, "PetFood": {"TargetConsumptionBy": "", "Feed": {"Instructions": "", "Type": ""}, "FoodStatetment": {"Additive": "", "AnalyticalConstituents": "", "Composition": ""}}, "Medicine": {"EAN": ""}, "DrugStore": {"Store": {"Origin": "Geproduceerd in Duitsland. Met melk en aardbeienpreparaat uit de EU", "Number": {"RVG": "", "RVH": ""}, "Certification": {"Agency": "", "Standard": ""}}, "Dosage": {"Admnistration": "", "Recommendation": ""}, "SideEffectsAndWarnings": ""}, "HealthCare": {"UsageAge": {"Description": "", "Max": {"UoM": "", "Value": 0}, "Min": {"UoM": "", "Value": 0}}, "SunProtection": {"Category": "", "Factor": ""}}, "LightBulb": {"BaseType": "", "LampTypeCode": "", "NumberOfSwitches": "", "SuitableForAccentLighting": "", "DeclaredPower": {"UoM": "", "Value": 0}, "EquivalentPower": {"UoM": "", "Value": 0}, "Diameter": {"UoM": "", "Value": 0}, "VisibleLight": {"UoM": "", "Value": 0}, "ColourTemperature": {"Avg": {"UoM": "", "Value": 0}, "Max": {"UoM": "", "Value": 0}, "Min": {"UoM": "", "Value": 0}}, "WarmUpTime": {"UoM": "", "Value": 0}}, "Battery": {"Voltage": {"UoM": "", "Value": "0"}, "Capacity": {"UoM": "", "Value": 0}, "Weight": {"UoM": "", "Value": "0"}, "Quantity": 0, "MaterialAgency": "", "Type": "", "TechnologyTypes": {"List": [], "EmptyListItem": ""}, "IsRechargeable": false, "BuiltIn": {"IsBuiltIn": false, "Quantity": 0}}, "Hazardous": {"ChildSafeClosure": "", "Chemical": {"Identification": "", "Name": "", "Organisation": "", "Concentration": 0}, "SafetyRecommendations": {"List": [], "EmptyListItem": {"Key": "", "Value": ""}}, "HazardDesignations": {"List": [], "EmptyListItem": {"Key": "", "Value": ""}}, "GHSSignal": {"Symbols": "", "Word": ""}}, "IsVisibleSection": {"AboutThisBeer": false, "AboutThisProduct": false, "AboutThisWine": false, "AllergieInfo": true, "HandyInfo": true, "Ingredients": true, "LegalInfo": true, "NutrionalValues": true, "PreparationInstruction": false, "ServingSuggestions": false, "SupplierContact": true, "TasteInfo": false, "UsageAndStorage": true}, "IsNoIndex": false}, "LegalInfoText": "", "ProductClassificationId": "", "MedicineURL": "", "IsUnderAge": false, "HasShoppingLists": false, "ImageURL": "https://images.ctfassets.net/s0lodsnpsezb/322966_M/e7efc4b21a5d90b5134f5197d52ad35a/322966.png", "Label": "", "OfflineSaleOnlyMessage": ""}}